leonard/__init__.py
leonard/__main__.py
leonard/_version.py
leonard/app.py
leonard-0.0.1.dist-info/LICENSE
leonard-0.0.1.dist-info/METADATA
leonard-0.0.1.dist-info/WHEEL
leonard-0.0.1.dist-info/entry_points.txt
leonard-0.0.1.dist-info/top_level.txt
leonard-0.0.1.dist-info/RECORD
