Metadata-Version: 2.1
Name: leonard
Version: 0.0.1
Summary: Configurable fast-access toolset
Home-page: https://github.com/es7s/leonard
Author: Aleksandr Shavykin
Author-email: 0.delameter@gmail.com
Classifier: Environment :: Console
Classifier: Intended Audience :: Developers
Classifier: Intended Audience :: Science/Research
Classifier: Intended Audience :: System Administrators
Classifier: Programming Language :: Python :: 3
Classifier: License :: OSI Approved :: MIT License
Classifier: Operating System :: OS Independent
Requires-Python: >=3.10
License-File: LICENSE
Requires-Dist: pytermor
